{"Q103, Q109": {"map": {"free_disk_space": "available_space", "new_size": "size", "new_file_size": "size", "spacer": "space", "size_to_append": "size_difference", "size_to_inc": "size_difference", "space_availablebool": "available_space", "disk": "available_space", "disk_free_size": "available_space", "available_dosk_space": "available_space", "size_to_enlarge": "size_difference", "disk_free_bytes": "available_space", "size_to_increase": "size_difference", "d_new_size": "size", "add": "size_difference", "resize_to": "size", "factor": "factor", "available_size": "available_space", "n_additional_file_size": "size_difference", "bytes_to_enhance": "size_difference", "free_space": "available_space", "enlarge_by_bytes": "size_difference", "available_bytes": "available_space", "increas_by": "size_difference", "space_available_on_disk": "available_space", "availabl_space": "available_space", "size_left": "available_space", "room_in_disk": "available_space", "available_space": "available_space", "avail_place": "available_space", "free_disk_space_bytes": "available_space", "available_disk_space": "available_space", "disk_avilable_place": "available_space", "free_space_size": "available_space", "space": "available_space", "update_size": "update_size", "free_memory": "available_space", "increase": "size_difference", "additional_size": "size_difference", "size_to_add": "size_difference", "available": "available_space", "data_amount": "amount", "newsize": "size", "expansion_in_bytes": "size_difference", "fs_file_system": "file_system", "by": "size_difference", "c_file": "file", "delta_bytes": "size_difference", "size_increase": "size_difference", "disk_free_sie": "available_space", "fre_size_on_dic": "available_space", "size_to_check": "size_to_check", "add_size": "size_difference", "space_left": "available_space", "size": "size", "currently_available": "available_space", "system": "system", "avail": "available_space", "required_space": "required_size", "f_size": "size", "to_add": "size_difference", "resize": "resize", "disk_capacity": "disk_capacity", "f": "file", "bytes_to_add": "size_difference", "disk_free_space": "available_space", "increment": "size_difference", "int": "int", "file_name": "file_name", "empty_space_on_disc": "available_space", "file": "file", "file_to_expand": "file", "open_space_in_disc": "available_space", "inc": "size_difference", "avail_space": "available_space", "news_size": "size", "enlarge": "size_difference", "inc_by": "size_difference", "expansion_size": "size_difference", "avilbie_siz": "available_space", "fp": "file", "extra_size": "size_difference", "resize_by": "size_difference", "cur_free_space": "available_space", "increase_size": "size_difference", "disk_size": "disk_capacity", "increase_by": "size_difference", "n_available_disk_space": "available_space", "by_amount": "size_difference", "add_space_size": "size_difference"}, "cat": ["file", "size", "available_space", "size_difference", "factor", "size_to_check", "update_size", "disk_capacity", "file_name", "system", "required_size", "space", "file_system", "int", "resize", "amount"]}, "Q155, Q30": {"map": {"num_of_mines": "number of mines", "board_size": "size", "size_of_board": "size", "mines_num": "number of mines", "cols": "columns", "height": "height", "num_mines": "number of mines", "grid_width": "width", "board_rows": "rows", "size": "size", "num_mokesh": "number of mines", "dim_board": "dimensions", "rows": "rows", "length": "length", "dimensions": "dimensions", "area": "area", "mines_number": "number of mines", "border_size": "size", "num_mimes": "number of mines", "gride_size": "size", "grid_y": "height", "grid_x": "width", "grid_height": "height", "board_width": "width", "num_rows": "rows", "demention_level": "dimensions", "mine_count": "number of mines", "grid_w": "width", "bombs": "number of mines", "n_mines": "number of mines", "mines": "number of mines", "num_ofmines": "number of mines", "boards_width": "width", "hight": "height", "board_cols": "columns", "size_mines": "size_mines", "board_height": "height", "gridsize": "size", "mines_count": "number of mines", "square_area": "area", "num_bombs": "number of mines", "mines_amount": "number of mines", "a": "a", "dim": "dimensions", "b": "b", "mine_n": "number of mines", "grid_size": "size", "num_of_bombs": "number of mines", "bombs_num": "number of mines", "h": "height", "m": "m", "num_miness": "number of mines", "n": "n", "nummines": "number of mines", "num_cols": "columns", "number_of_mines": "number of mines", "w": "width", "num_of_boms": "number of mines", "y": "height", "x": "width", "total_mines": "number of mines", "width": "width"}, "cat": ["size", "number of mines", "width", "height", "dimensions", "rows", "columns", "a", "b", "m", "area", "length", "n", "size_mines"]}, "Q84, Q96a, Q97": {"map": {"game_screen": "board", "cur_game_board": "board", "current_state": "game_state", "game_board": "board", "player": "player", "y_locations": "y_locations", "gameboard_state": "game_state", "player_id": "player", "table": "board", "c_state": "game_state", "size": "board_size", "current_game_state": "game_state", "matrix": "board", "mat_state": "game_state", "self": "self", "player2": "player2", "board_state": "game_state", "state": "game_state", "player1": "player1", "board": "board", "cur_board": "board", "current_board": "board", "game_state": "game_state", "mat": "board", "cur_board_state": "game_state", "tic_tac_toe_board": "board", "user_output": "user_output", "step": "step", "grid": "board", "user_id": "player", "board_mat": "board", "a": "list", "b": "board", "current_board_status": "game_state", "m": "board_height", "x_locations": "x_locations", "n": "board_width", "turn": "step", "game_node": "game_node"}, "cat": ["board", "game_state", "board_size", "game_node", "player", "board_width", "board_height", "step", "player1", "player2", "user_output", "x_locations", "y_locations", "list", "self"]}, "Q111, Q117": {"map": {"vanile": "ice_cream", "recipe": "recipe", "vanila": "ice_cream", "num_vanilla_ice_cream_cups": "ice_cream", "choc_bisk_n": "biscuits", "choco": "biscuits", "baking_ppr_h": "paper_height", "wraps": "paper", "h_alum": "paper_height", "wrap_height": "paper_height", "wrapping_paper_height": "paper_height", "num_of_papers": "paper_count", "wrap_width": "paper_width", "biacuits": "biscuits", "d_ice_cream_amount": "ice_cream", "paper_cm_sq": "paper_size", "biacuits_num": "biscuits", "num_of_biscuits": "biscuits", "iceream": "ice_cream", "ingredient_types": "ingredient_types", "num_choco": "biscuits", "ice_cream_in_mil": "ice_cream", "b": "biscuits", "paper_height": "paper_height", "wrapper_width": "paper_width", "wrapping_paper_in_square_meters": "paper_size", "hald_ice_cream_cup": "ice_cream", "bicuit_amout": "biscuits", "bis": "biscuits", "ice_cream_cups": "ice_cream", "width_plastic": "paper_width", "number_of_biscuits": "biscuits", "p": "paper", "paper": "paper", "paper_width": "paper_width", "vanilla_cups": "ice_cream", "biscuits": "biscuits", "vanilla": "ice_cream", "van_icecream_n": "ice_cream", "num_of_bisquits": "biscuits", "papaer": "paper_size", "vanilla_ice_cream_cups": "ice_cream", "num_chocolate_biscuits": "biscuits", "wrap_h": "paper_height", "wrap_w": "paper_width", "choclate_biscuts": "biscuits", "n_biskwits": "biscuits", "chock": "biscuits", "rappaper": "paper", "wrapping_paper_wid": "paper_width", "paper_width_cm": "paper_width", "icecream": "ice_cream", "paper_length_cm": "paper_length", "papers": "paper_count", "vainl": "ice_cream", "numpapers": "paper_count", "w_alum": "paper_width", "wrapping": "paper", "paper_area": "paper_size", "paper_amount": "paper_count", "biscuit": "biscuits", "wrapper_height": "paper_height", "num_vanilla_cups": "ice_cream", "wrapper_length": "paper_length", "bisq": "biscuits", "paper_size": "paper_size", "paper_length": "paper_length", "length": "paper_length", "bisk": "biscuits", "shoko_bis": "biscuits", "bisc": "biscuits", "icecream_amount": "ice_cream", "icecream_cups": "ice_cream", "chocolate_biscuit_quantity": "biscuits", "wodth": "paper_width", "n_shell_width": "paper_width", "height": "paper_height", "n_biscuits": "biscuits", "wrap": "paper", "n_of_cups": "ice_cream", "wrap_paper": "paper", "biscuits_num": "biscuits", "num_paper": "paper_count", "area": "paper_size", "wrapper": "paper", "wrapping_paper_len": "paper_length", "width": "paper_width", "wrapping_height": "paper_height", "num_vanille": "ice_cream", "paper_quantity": "paper_count", "wrapping_paper": "paper", "chocolate_biscuits": "biscuits", "num_wrapping_papers": "paper_count", "chocolate": "biscuits", "wrap_length": "paper_length", "rapping_page_size": "paper_size", "amount_of_ingredients": "ingredient_count", "bisquits_num": "biscuits", "vanilla_cups_num": "ice_cream", "n_shell_height": "paper_height", "amont_of_milk": "ice_cream", "num_of_biscuit": "biscuits", "height_plastic": "paper_height", "cups_of_icecream": "ice_cream", "wrapping_paper_width": "paper_width", "v": "ice_cream", "baking_ppr_w": "paper_width", "wrapping_width": "paper_width", "cups_vanila": "ice_cream", "canul": "ice_cream", "cups_of_ice_cream": "ice_cream", "bisc_num": "biscuits", "wrapping_paper_size": "paper_size", "ice_creams": "ice_cream", "ice_cream_glasses": "ice_cream", "rap": "paper", "wrapping_length": "paper_length", "ic": "ice_cream", "paper_len": "paper_length", "cream": "ice_cream", "vanil_ice_creem_amount": "ice_cream", "num_vailla_cups": "ice_cream", "num_of_vanille_cups": "ice_cream", "cups_of_vanilla": "ice_cream", "inventory": "inventory", "ice_cresm": "ice_cream", "wrappers": "paper_count", "vanilla_icecream": "ice_cream", "cups": "ice_cream", "amount_of_icecream": "ice_cream", "num_biscuits": "biscuits", "ice_cream": "ice_cream", "chocko": "biscuits", "ingredient_amount": "ingredient_count", "height_paper": "paper_height", "ice_cup": "ice_cream", "width_paper": "paper_width"}, "cat": ["biscuits", "ice_cream", "paper_height", "paper_width", "paper_length", "paper_size", "paper_count", "paper", "inventory", "ingredient_count", "ingredient_types", "recipe"]}, "Q139, Q144": {"map": {"num_pinukim_done": "used_benefits", "pinuk_used_already": "used_benefits", "used_treats": "used_benefits", "current_month_benefits_used": "used_benefits", "entitledbenefits": "entitled_benefits", "monthly_bonuses": "entitled_benefits", "current_month_used": "used_benefits", "client_benefits": "used_benefits", "earned": "entitled_benefits", "gifts_used": "used_benefits", "usable_pampers": "entitled_benefits", "points_to_use": "used_benefits", "amount_needed": "needed_benefits", "current_month_benefits": "entitled_benefits", "get": "entitled_benefits", "current_month_entitlement": "entitled_benefits", "current_num_of_benefits_used": "used_benefits", "current_num_of_benefits": "entitled_benefits", "pinuks_used": "used_benefits", "already_used_gifts": "used_benefits", "benefits_entitlrd": "entitled_benefits", "used_benefits": "used_benefits", "user_used_gifts": "used_benefits", "num_pinukim": "entitled_benefits", "this_month_benefits": "entitled_benefits", "cur_benefits": "entitled_benefits", "used_gifts": "used_benefits", "current_month_used_benefits_count": "used_benefits", "deserved_pinuks": "entitled_benefits", "entitled_benefits": "entitled_benefits", "num": "num_benefits", "gifts_won": "entitled_benefits", "num_used_gifts": "used_benefits", "total": "entitled_benefits", "entitled_benefits_per_month": "entitled_benefits", "num_available_gifts": "entitled_benefits", "availble_credit": "entitled_benefits", "num_used": "used_benefits", "num_of_benefits_entitled": "entitled_benefits", "month_bonus": "entitled_benefits", "customer_id": "client_id", "num_entitled": "entitled_benefits", "benefits_used": "used_benefits", "benefits_entitlement": "entitled_benefits", "used_credit": "used_benefits", "num_used_benefits": "used_benefits", "points_have": "entitled_benefits", "n_entitled_benefits": "entitled_benefits", "num_of_benefits": "entitled_benefits", "used_bonuses_so_far": "used_benefits", "benefits": "entitled_benefits", "curr_month_benefits": "entitled_benefits", "deserved": "entitled_benefits", "credit": "entitled_benefits", "used_perks": "used_benefits", "n_gifts_used": "used_benefits", "num_entitled_benefits": "entitled_benefits", "canget": "entitled_benefits", "total_benefits": "entitled_benefits", "num_benefits_for_month": "entitled_benefits", "num_entitles_benefits": "entitled_benefits", "current_num_benecits": "entitled_benefits", "n_gifts_in_current_month": "entitled_benefits", "current_month_usage": "used_benefits", "benefits_balance": "entitled_benefits", "amount_used": "used_benefits", "gained": "entitled_benefits", "gained_treats": "entitled_benefits", "consumed_num_of_benefits": "used_benefits", "pinukim_may_use": "entitled_benefits", "gifts_amount": "entitled_benefits", "client_prize_num": "entitled_benefits", "current_month_benefits_entitled": "entitled_benefits", "current_benefits_used": "used_benefits", "monthly_gifts_left": "remaining_benefits", "starting_balance": "entitled_benefits", "user_owned_gifts": "entitled_benefits", "n_benefits_month": "entitled_benefits", "needed_pampers": "used_benefits", "month_spent_bonus": "used_benefits", "accumulated_benefits": "entitled_benefits", "n_benefits_used": "used_benefits", "current_month_entitlness": "entitled_benefits", "num_potential_benefits": "entitled_benefits", "current_number_of_treats": "entitled_benefits", "n_used_benefits": "used_benefits", "number_of_benefits_used": "used_benefits", "current_month_benefits_count": "entitled_benefits", "number_of_benefits_to_grant": "entitled_benefits", "entitled_treats": "entitled_benefits", "current_benefits_entitlement": "entitled_benefits", "entitled": "entitled_benefits", "used": "used_benefits", "benefits_number": "entitled_benefits", "gifts": "entitled_benefits", "remaining_perks": "remaining_benefits", "client_prize_used": "used_benefits", "recieved": "entitled_benefits", "request": "needed_benefits", "spent": "used_benefits", "client": "client_id", "u": "client_id"}, "cat": ["entitled_benefits", "used_benefits", "remaining_benefits", "client_id", "num_benefits", "needed_benefits"]}, "Q84, Q96a": {"cat": ["board_category", "state", "state", "others", "turn"], "map": {"board": "board_category", "board_state": "state", "parameters": "state", "row": "state", "col": "state", "grid": "state", "current_game_state": "state", "cur_board_state": "state", "invalid": "board_category", "game_screen": "state", "board_mat": "board_category", "self": "board_category", "current_state": "state", "c_state": "state", "step": "others", "game_state": "state", "current_board_status": "state", "turn": "turn", "game_board": "board_category", "void": "others", "mat_state": "state"}}, "Q103": {"cat": ["file", "increment", "avail"], "map": {"file": "file", "increment": "increment", "available_space": "avail", "inc_space": "increment", "avail_space": "avail", "add": "increment", "remaining": "avail", "increase": "increment", "space_available": "avail", "additional_bytes": "avail", "increase_by": "increment", "used_space": "avail", "add_size": "increment", "size_left": "avail", "fp": "file", "space_left": "avail", "new_size": "increment", "size_to_increase": "increment", "space_available_on_disk": "avail", "file_to_expand": "file", "expansion_size": "increment", "free_space": "avail", "required_space": "increment", "free_disk_space": "avail", "data_amount": "increment", "bytes_to_enhance": "increment", "disk_free_bytes": "avail", "delta_bytes": "increment", "free_disk_space_bytes": "avail", "size": "increment", "increas_by": "increment", "invalid": "increment", "f": "file", "space": "avail", "newsize": "increment", "available": "avail", "spacer": "avail", "enlarge": "increment", "add_space_size": "increment", "free_space_size": "avail", "by_amount": "increment", "disk_capacity": "avail"}}, "Q117": {"cat": ["biscuits", "ice_cream", "paper", "invalid", "parameters"], "map": {"biscuits": "biscuits", "ice_cream": "ice_cream", "wrapping_paper": "paper", "biscuit_count": "biscuits", "ice_cream_amount": "ice_cream", "invalid": "invalid", "choco_bis": "biscuits", "vanilla": "ice_cream", "paper": "paper", "parameters": "parameters", "icecream": "ice_cream", "length": "paper", "width": "paper", "ice_cream_cups": "paper", "papers": "paper", "bis": "biscuits", "hald_ice_cream_cup": "ice_cream", "wrap_width": "paper", "wrap_height": "paper", "number_of_biscuits": "biscuits", "cups_of_ice_cream": "ice_cream", "wrapping_paper_in_square_meters": "paper", "icecream_cups": "ice_cream", "wrap_paper": "paper", "wrapper_width": "paper", "wrapper_height": "paper", "chock": "biscuits", "vanila": "ice_cream", "wrap": "paper", "biscuit": "biscuits", "biacuits_num": "biscuits", "paper_area": "paper", "n_biscuits": "biscuits", "n_of_cups": "ice_cream", "area": "paper", "b": "biscuits", "v": "ice_cream", "p": "paper", "num_biscuits": "biscuits", "num_vanilla_cups": "ice_cream", "paper_length_cm": "paper", "paper_width_cm": "paper", "wrappers": "paper", "wrapping_paper_width": "paper", "wrapping_paper_height": "paper"}}, "Q139": {"cat": ["monthly_benefits", "max_benefits", "invalid", "user"], "map": {"monthly_benefits": "monthly_benefits", "max_benefits": "max_benefits", "invalid": "invalid", "max": "max_benefits", "used": "monthly_benefits", "benefits_awarded": "max_benefits", "benefits_used": "monthly_benefits", "max_benefits_per_month": "max_benefits", "entitled": "max_benefits", "benefits": "max_benefits", "num_potential_benefits": "max_benefits", "num_used_benefits": "monthly_benefits", "number_of_benefits_to_grant": "max_benefits", "number_of_benefits_used": "monthly_benefits", "starting_balance": "max_benefits", "amount_used": "monthly_benefits", "benefits_entitlement": "max_benefits", "benefits_balance": "monthly_benefits", "used_benefits": "monthly_benefits", "entitled_benefits": "max_benefits", "current_month_entitlement": "max_benefits", "current_month_usage": "monthly_benefits", "curr_month_benefits": "max_benefits", "entitled_benefits_per_month": "monthly_benefits", "current_num_of_benefits": "max_benefits", "current_num_of_benefits_used": "monthly_benefits", "u": "user", "entitledbenefits": "monthly_benefits", "current_benefits_entitlement": "max_benefits", "current_benefits_used": "monthly_benefits", "client": "user", "num_benefits_for_month": "max_benefits", "accumulated_benefits": "monthly_benefits", "n_entitled_benefits": "max_benefits", "n_used_benefits": "monthly_benefits", "total_benefits": "max_benefits", "current_month_benefits_count": "monthly_benefits", "current_month_used_benefits_count": "monthly_benefits", "this_month_benefits": "max_benefits"}}}